{
	"name": "ds_target_copy_tables_foreach",
	"properties": {
		"linkedServiceName": {
			"referenceName": "ls_AzureDataLakeStoragegen2",
			"type": "LinkedServiceReference"
		},
		"annotations": [],
		"type": "DelimitedText",
		"typeProperties": {
			"location": {
				"type": "AzureBlobFSLocation",
				"folderPath": "Target/foreachtables",
				"fileSystem": "adlsgen2container"
			},
			"columnDelimiter": ",",
			"escapeChar": "\\",
			"firstRowAsHeader": false,
			"quoteChar": "\""
		},
		"schema": []
	},
	"type": "Microsoft.DataFactory/factories/datasets"
}